{"url":"https:\/\/tinger.bitrix24.ru\/rest\/190\/42tc2gxq8od2858i\/crm.lead.add.json","info":{"url":"https:\/\/tinger.bitrix24.ru\/rest\/190\/42tc2gxq8od2858i\/crm.lead.add.json","content_type":"application\/json; charset=utf-8","http_code":200,"header_size":1028,"request_size":207,"filetime":-1,"ssl_verify_result":0,"redirect_count":0,"total_time":3.007406,"namelookup_time":0.01375,"connect_time":0.018959,"pretransfer_time":0.031068999999999999,"size_upload":1493,"size_download":287,"speed_download":95,"speed_upload":496,"download_content_length":-1,"upload_content_length":1493,"starttransfer_time":0.031071000000000001,"redirect_time":0,"redirect_url":"","primary_ip":"178.132.201.50","certinfo":[],"primary_port":443,"local_ip":"188.225.57.79","local_port":49676,"http_version":3,"protocol":2,"ssl_verifyresult":0,"scheme":"HTTPS","appconnect_time_us":30956,"connect_time_us":18959,"namelookup_time_us":13750,"pretransfer_time_us":31069,"redirect_time_us":0,"starttransfer_time_us":31071,"total_time_us":3007406},"params":{"method":"crm.lead.add","params":{"fields":{"UF_CRM_1449663065":"9600","SOURCE_ID":"CONFERENCE","ASSIGNED_BY_ID":58,"TITLE":"\u041a\u0443\u043f\u0438\u0442\u044c \u041b\u0438\u0441\u0442 \u041f\u041d\u0414 3000x1500x2 \u043c\u043c, \u043d\u0430\u0442\u0443\u0440\u0430\u043b\u044c\u043d\u044b\u0439","NAME":"\u0410\u043b\u0435\u043a\u0441\u0430\u043d\u0434\u0440\u0430","PHONE":[{"VALUE":"+7 (903) 569-67-87","VALUE_TYPE":"WORK"}],"EMAIL":[{"VALUE":null,"VALUE_TYPE":"WORK"}],"COMMENTS":"","TRACE":"{\u0022url\u0022:\u0022https:\/\/tingerplast.ru\/listovoy-plastik-pnd\/list-pnd-3000x1500x2-mm-naturalnyy\/\u0022,\u0022ref\u0022:\u0022https:\/\/www.google.com\/\u0022,\u0022device\u0022:{\u0022isMobile\u0022:false},\u0022tags\u0022:{\u0022ts\u0022:1698069441,\u0022list\u0022:{},\u0022gclid\u0022:null},\u0022client\u0022:{\u0022yaId\u0022:\u0022169806944178366324\u0022},\u0022pages\u0022:{\u0022list\u0022:[[\u0022https:\/\/tingerplast.ru\/listovoy-plastik-pnd\/\u0022,1698069441,\u0022\u041b\u0438\u0441\u0442\u043e\u0432\u043e\u0439 \u043f\u043b\u0430\u0441\u0442\u0438\u043a \u041f\u041d\u0414\u0022],[\u0022https:\/\/tingerplast.ru\/listovoy-plastik-pnd\/list-pnd-3000x1500x2-mm-naturalnyy\/\u0022,1698071112,\u0022\u041b\u0438\u0441\u0442 \u041f\u041d\u0414 3000x1500x2 \u043c\u043c, \u043d\u0430\u0442\u0443\u0440\u0430\u043b\u044c\u043d\u044b\u0439\u0022]]},\u0022gid\u0022:null,\u0022previous\u0022:{\u0022list\u0022:[]}}"}}},"result":{"result":479824,"time":{"start":1698071124.201746,"finish":1698071127.094583,"duration":2.8928370475769043,"processing":2.8365747928619385,"date_start":"2023-10-23T17:25:24+03:00","date_finish":"2023-10-23T17:25:27+03:00","operating_reset_at":1698071724,"operating":2.8365418910980225}}}