{"url":"https:\/\/tinger.bitrix24.ru\/rest\/190\/42tc2gxq8od2858i\/crm.contact.add.json","info":{"url":"https:\/\/tinger.bitrix24.ru\/rest\/190\/42tc2gxq8od2858i\/crm.contact.add.json","content_type":"application\/json; charset=utf-8","http_code":200,"header_size":1029,"request_size":209,"filetime":-1,"ssl_verify_result":0,"redirect_count":0,"total_time":0.38113999999999998,"namelookup_time":0.0012019999999999999,"connect_time":0.0039699999999999996,"pretransfer_time":0.017434000000000002,"size_upload":250,"size_download":291,"speed_download":763,"speed_upload":656,"download_content_length":-1,"upload_content_length":250,"starttransfer_time":0.017436,"redirect_time":0,"redirect_url":"","primary_ip":"178.132.201.53","certinfo":[],"primary_port":443,"local_ip":"188.225.57.79","local_port":37794,"http_version":3,"protocol":2,"ssl_verifyresult":0,"scheme":"HTTPS","appconnect_time_us":17346,"connect_time_us":3970,"namelookup_time_us":1202,"pretransfer_time_us":17434,"redirect_time_us":0,"starttransfer_time_us":17436,"total_time_us":381140},"params":{"method":"crm.contact.add","params":{"fields":{"UF_CRM_566E8F1A1E899":170,"PHONE":[{"VALUE":"+7 (388) 423-42-34","VALUE_TYPE":"WORK"}],"EMAIL":[{"VALUE":"","VALUE_TYPE":"WORK"}],"NAME":"zxczxc"}}},"result":{"result":63586,"time":{"start":1691476077.9033971,"finish":1691476078.2128861,"duration":0.30948901176452637,"processing":0.27718710899353027,"date_start":"2023-08-08T09:27:57+03:00","date_finish":"2023-08-08T09:27:58+03:00","operating_reset_at":1691476677,"operating":0.97460293769836426}}}