{"url":"https:\/\/tinger.bitrix24.ru\/rest\/190\/42tc2gxq8od2858i\/crm.lead.add.json","info":{"url":"https:\/\/tinger.bitrix24.ru\/rest\/190\/42tc2gxq8od2858i\/crm.lead.add.json","content_type":"application\/json; charset=utf-8","http_code":200,"header_size":1105,"request_size":206,"filetime":-1,"ssl_verify_result":0,"redirect_count":0,"total_time":2.899986,"namelookup_time":0.002768,"connect_time":0.013943,"pretransfer_time":0.038602,"size_upload":904,"size_download":288,"speed_download":99,"speed_upload":311,"download_content_length":-1,"upload_content_length":904,"starttransfer_time":0.038606,"redirect_time":0,"redirect_url":"","primary_ip":"46.235.53.69","certinfo":[],"primary_port":443,"local_ip":"188.225.57.79","local_port":44482,"http_version":3,"protocol":2,"ssl_verifyresult":0,"scheme":"HTTPS","appconnect_time_us":38468,"connect_time_us":13943,"namelookup_time_us":2768,"pretransfer_time_us":38602,"redirect_time_us":0,"starttransfer_time_us":38606,"total_time_us":2899986},"params":{"method":"crm.lead.add","params":{"fields":{"SOURCE_ID":"WEB","ASSIGNED_BY_ID":58,"TITLE":"TINGER.RU | \u0417\u0430\u043a\u0430\u0437 \u043f\u043d\u0435\u0432\u043c\u043e\u0434\u0438\u0441\u043a\u043e\u0432","TAG":"TINGER.RU","NAME":"\u0415\u0432\u0433\u0435\u043d\u0438\u0439 ","SECOND_NAME":"","LAST_NAME":"","UF_CRM_1517561552":"3290487","UTM_SOURCE":"yandex","UTM_MEDIUM":"cpc","UTM_CAMPAIGN":"rsya_diski","UTM_CONTENT":"12564762845","UTM_TERM":"\u0434\u0438\u0441\u043a\u0438 \u043d\u0430 \u043a\u0430\u0440\u0430\u043a\u0430\u0442 \u043a\u0443\u043f\u0438\u0442\u044c","PHONE":[{"VALUE":"8 (919) 445-89-84","VALUE_TYPE":"WORK"}],"COMMENTS":"\u041f\u0430\u0440\u0430\u043c\u0435\u0442\u0440\u044b \u0434\u0438\u0441\u043a\u0430:\u003Cbr\u003E\u003Cbr\u003E","UF_CRM_1449663065":"16522"}}},"result":{"result":413494,"time":{"start":1669796560.736961,"finish":1669796563.502414,"duration":2.7654531002044678,"processing":2.732758045196533,"date_start":"2022-11-30T11:22:40+03:00","date_finish":"2022-11-30T11:22:43+03:00","operating_reset_at":1669797160,"operating":6.608465909957886}}}