{"url":"https:\/\/tinger.bitrix24.ru\/rest\/190\/42tc2gxq8od2858i\/crm.lead.add.json","info":{"url":"https:\/\/tinger.bitrix24.ru\/rest\/190\/42tc2gxq8od2858i\/crm.lead.add.json","content_type":"application\/json; charset=utf-8","http_code":200,"header_size":1028,"request_size":207,"filetime":-1,"ssl_verify_result":0,"redirect_count":0,"total_time":3.4802369999999998,"namelookup_time":0.0018799999999999999,"connect_time":0.0030899999999999999,"pretransfer_time":0.012789,"size_upload":1135,"size_download":286,"speed_download":82,"speed_upload":326,"download_content_length":-1,"upload_content_length":1135,"starttransfer_time":0.012792,"redirect_time":0,"redirect_url":"","primary_ip":"178.132.201.50","certinfo":[],"primary_port":443,"local_ip":"188.225.57.79","local_port":47724,"http_version":3,"protocol":2,"ssl_verifyresult":0,"scheme":"HTTPS","appconnect_time_us":12691,"connect_time_us":3090,"namelookup_time_us":1880,"pretransfer_time_us":12789,"redirect_time_us":0,"starttransfer_time_us":12792,"total_time_us":3480237},"params":{"method":"crm.lead.add","params":{"fields":{"UF_CRM_1449663065":"9600","SOURCE_ID":"CONFERENCE","ASSIGNED_BY_ID":58,"TITLE":"\u041a\u0443\u043f\u0438\u0442\u044c \u041b\u0438\u0441\u0442 \u041f\u041f 3000x1500x15 \u043c\u043c, \u0447\u0451\u0440\u043d\u044b\u0439","NAME":"\u0410\u0440\u0442\u0451\u043c ","PHONE":[{"VALUE":"+7 (961) 721-57-27","VALUE_TYPE":"WORK"}],"EMAIL":[{"VALUE":null,"VALUE_TYPE":"WORK"}],"COMMENTS":"","TRACE":"{\u0022url\u0022:\u0022https:\/\/tingerplast.ru\/listovoy-plastik-pp\/list-pp-3000x1500x15-mm-chyernyy\/\u0022,\u0022device\u0022:{\u0022isMobile\u0022:true},\u0022tags\u0022:{\u0022ts\u0022:1689156297,\u0022list\u0022:{},\u0022gclid\u0022:null},\u0022client\u0022:{\u0022yaId\u0022:\u00221689156298287519284\u0022},\u0022pages\u0022:{\u0022list\u0022:[[\u0022https:\/\/tingerplast.ru\/listovoy-plastik-pp\/list-pp-3000x1500x15-mm-chyernyy\/\u0022,1689156298,\u0022\u041b\u0438\u0441\u0442 \u041f\u041f 3000x1500x15 \u043c\u043c, \u0447\u0451\u0440\u043d\u044b\u0439\u0022]]},\u0022gid\u0022:null,\u0022previous\u0022:{\u0022list\u0022:[]}}"}}},"result":{"result":456608,"time":{"start":1689157111.63779,"finish":1689157115.0198541,"duration":3.3820641040802002,"processing":3.331063985824585,"date_start":"2023-07-12T13:18:31+03:00","date_finish":"2023-07-12T13:18:35+03:00","operating_reset_at":1689157711,"operating":3.3310410976409912}}}