{"url":"https:\/\/tinger.bitrix24.ru\/rest\/190\/42tc2gxq8od2858i\/crm.contact.add.json","info":{"url":"https:\/\/tinger.bitrix24.ru\/rest\/190\/42tc2gxq8od2858i\/crm.contact.add.json","content_type":"application\/json; charset=utf-8","http_code":200,"header_size":1034,"request_size":209,"filetime":-1,"ssl_verify_result":0,"redirect_count":0,"total_time":0.38463999999999998,"namelookup_time":0.001652,"connect_time":0.016225,"pretransfer_time":0.039197000000000003,"size_upload":384,"size_download":287,"speed_download":747,"speed_upload":1000,"download_content_length":-1,"upload_content_length":384,"starttransfer_time":0.039198999999999998,"redirect_time":0,"redirect_url":"","primary_ip":"46.235.53.58","certinfo":[],"primary_port":443,"local_ip":"188.225.57.79","local_port":41392,"http_version":3,"protocol":2,"ssl_verifyresult":0,"scheme":"HTTPS","appconnect_time_us":39128,"connect_time_us":16225,"namelookup_time_us":1652,"pretransfer_time_us":39197,"redirect_time_us":0,"starttransfer_time_us":39199,"total_time_us":384640},"params":{"method":"crm.contact.add","params":{"fields":{"UF_CRM_566E8F1A1E899":170,"ASSIGNED_BY_ID":50856,"PHONE":[{"VALUE":"8 (911) 531-66-21","VALUE_TYPE":"WORK"}],"EMAIL":[{"VALUE":"stydenko.arina2018@yandex.ru","VALUE_TYPE":"WORK"}],"NAME":"\u0421\u0442\u044b\u0434\u0435\u043d\u043a\u043e \u0410\u0440\u0438\u043d\u0430 "}}},"result":{"result":88700,"time":{"start":1757335850.0467179,"finish":1757335850.3263299,"duration":0.27961206436157227,"processing":0.24385690689086914,"date_start":"2025-09-08T15:50:50+03:00","date_finish":"2025-09-08T15:50:50+03:00","operating_reset_at":1757336450,"operating":0.2438349723815918}}}