{"url":"https:\/\/tinger.bitrix24.ru\/rest\/190\/42tc2gxq8od2858i\/crm.lead.add.json","info":{"url":"https:\/\/tinger.bitrix24.ru\/rest\/190\/42tc2gxq8od2858i\/crm.lead.add.json","content_type":"application\/json; charset=utf-8","http_code":200,"header_size":920,"request_size":207,"filetime":-1,"ssl_verify_result":0,"redirect_count":0,"total_time":2.046916,"namelookup_time":0.013542,"connect_time":0.014704,"pretransfer_time":0.024028000000000001,"size_upload":2029,"size_download":263,"speed_download":128,"speed_upload":991,"download_content_length":-1,"upload_content_length":2029,"starttransfer_time":0.024032000000000001,"redirect_time":0,"redirect_url":"","primary_ip":"178.132.201.53","certinfo":[],"primary_port":443,"local_ip":"188.225.57.79","local_port":44310,"http_version":3,"protocol":2,"ssl_verifyresult":0,"scheme":"HTTPS","appconnect_time_us":23918,"connect_time_us":14704,"namelookup_time_us":13542,"pretransfer_time_us":24028,"redirect_time_us":0,"starttransfer_time_us":24032,"total_time_us":2046916},"params":{"method":"crm.lead.add","params":{"fields":{"NAME":"\u0422\u0435\u0441\u044213.11","PHONE":[{"VALUE":"8 (956) 538-95-55","VALUE_TYPE":"WORK"}],"EMAIL":[{"VALUE":"","VALUE_TYPE":"WORK"}],"TRACE":"{\u0022url\u0022:\u0022https:\/\/tingard.ru\/?utm_content=gift\u0022,\u0022device\u0022:{\u0022isMobile\u0022:true},\u0022tags\u0022:{\u0022ts\u0022:1763042502,\u0022list\u0022:{\u0022utm_content\u0022:\u0022gift\u0022},\u0022gclid\u0022:null},\u0022client\u0022:{\u0022yaId\u0022:\u00221750309836643969347\u0022},\u0022pages\u0022:{\u0022list\u0022:[[\u0022https:\/\/tingard.ru\/?utm_source=yandex\u0026utm_medium=cpc\u0026utm_campaign=mk_rf_kval\u0026utm_content=17359044788\u0026utm_term=---autotargeting\u0026roistat=direct14_search_702036728_rsMasterGroup_rsMasterBanner_---autotargeting\u0026etext=2202.-KMko2ql9EFhdo_qCMnGbV8mfzdyMH9XJxcjx2INt992eWF6cHl4dHh1dGRtZWps.f353a3dd7cdf199b35f11325a54e857a45bb4c09\u0026yclid=18276750432812400639\u0026ybaip=1\u0022,1762810872,\u0022TINGARD \u2014 \u0431\u0435\u0441\u0448\u043e\u0432\u043d\u044b\u0439 \u043f\u043b\u0430\u0441\u0442\u0438\u043a\u043e\u0432\u044b\u0439 \u043f\u043e\u0433\u0440\u0435\u0431 \u0441\u0022],[\u0022https:\/\/tingard.ru\/?utm_content=gift\u0022,1763042502,\u0022TINGARD \u2014 \u0431\u0435\u0441\u0448\u043e\u0432\u043d\u044b\u0439 \u043f\u043b\u0430\u0441\u0442\u0438\u043a\u043e\u0432\u044b\u0439 \u043f\u043e\u0433\u0440\u0435\u0431 \u0441\u0022]]},\u0022gid\u0022:null,\u0022previous\u0022:{\u0022list\u0022:[]}}","UF_CRM_1736853511":"1750309836643969347","UF_CRM_1736853555":"1750309836643969347","UF_CRM_1736853537":"1750309836643969347","UF_CRM_1517561552":"3800542","COMMENTS":null,"TITLE":"\u041a\u043e\u043b\u0435\u0441\u043e \u043f\u043e\u0434\u0430\u0440\u043a\u043e\u0432 (\u041c\u043e\u043d\u0442\u0430\u0436\u043d\u044b\u0439 \u043a\u043e\u043c\u043f\u043b\u0435\u043a\u0442)","UF_CRM_1449663065":68,"ASSIGNED_BY_ID":58,"SOURCE_ID":9}}},"result":{"result":631994,"time":{"start":1763042529,"finish":1763042531.457077,"duration":2.4570770263671875,"processing":2,"date_start":"2025-11-13T17:02:09+03:00","date_finish":"2025-11-13T17:02:11+03:00","operating_reset_at":1763043129,"operating":3.2953989505767822}}}