{"url":"https:\/\/tinger.bitrix24.ru\/rest\/190\/42tc2gxq8od2858i\/crm.contact.add.json","info":{"url":"https:\/\/tinger.bitrix24.ru\/rest\/190\/42tc2gxq8od2858i\/crm.contact.add.json","content_type":"application\/json; charset=utf-8","http_code":200,"header_size":1034,"request_size":209,"filetime":-1,"ssl_verify_result":0,"redirect_count":0,"total_time":0.329152,"namelookup_time":0.001684,"connect_time":0.013867000000000001,"pretransfer_time":0.034937000000000003,"size_upload":398,"size_download":288,"speed_download":875,"speed_upload":1209,"download_content_length":-1,"upload_content_length":398,"starttransfer_time":0.034939999999999999,"redirect_time":0,"redirect_url":"","primary_ip":"46.235.53.69","certinfo":[],"primary_port":443,"local_ip":"188.225.57.79","local_port":39594,"http_version":3,"protocol":2,"ssl_verifyresult":0,"scheme":"HTTPS","appconnect_time_us":34854,"connect_time_us":13867,"namelookup_time_us":1684,"pretransfer_time_us":34937,"redirect_time_us":0,"starttransfer_time_us":34940,"total_time_us":329152},"params":{"method":"crm.contact.add","params":{"fields":{"UF_CRM_566E8F1A1E899":170,"ASSIGNED_BY_ID":50856,"PHONE":[{"VALUE":"8 (921) 256-37-75","VALUE_TYPE":"WORK"}],"EMAIL":[{"VALUE":"sashcanyrin1708@gmail.com","VALUE_TYPE":"WORK"}],"NAME":"\u0410\u043b\u0435\u043a\u0441\u0430\u043d\u0434\u0440 \u0421\u0430\u043f\u0443\u0440\u0438\u043d"}}},"result":{"result":88970,"time":{"start":1758702883.0144889,"finish":1758702883.251869,"duration":0.23738002777099609,"processing":0.21167612075805664,"date_start":"2025-09-24T11:34:43+03:00","date_finish":"2025-09-24T11:34:43+03:00","operating_reset_at":1758703483,"operating":0.21165919303894043}}}