{"url":"https:\/\/tinger.bitrix24.ru\/rest\/190\/42tc2gxq8od2858i\/crm.lead.add.json","info":{"url":"https:\/\/tinger.bitrix24.ru\/rest\/190\/42tc2gxq8od2858i\/crm.lead.add.json","content_type":"application\/json; charset=utf-8","http_code":200,"header_size":1031,"request_size":207,"filetime":-1,"ssl_verify_result":0,"redirect_count":0,"total_time":1.9369879999999999,"namelookup_time":0.001787,"connect_time":0.011002,"pretransfer_time":0.033034000000000001,"size_upload":1305,"size_download":289,"speed_download":149,"speed_upload":674,"download_content_length":-1,"upload_content_length":1305,"starttransfer_time":0.033037999999999998,"redirect_time":0,"redirect_url":"","primary_ip":"89.208.228.119","certinfo":[],"primary_port":443,"local_ip":"188.225.57.79","local_port":52086,"http_version":3,"protocol":2,"ssl_verifyresult":0,"scheme":"HTTPS","appconnect_time_us":32824,"connect_time_us":11002,"namelookup_time_us":1787,"pretransfer_time_us":33034,"redirect_time_us":0,"starttransfer_time_us":33038,"total_time_us":1936988},"params":{"method":"crm.lead.add","params":{"fields":{"UF_CRM_1449663065":null,"SOURCE_ID":"CONFERENCE","ASSIGNED_BY_ID":58,"TITLE":null,"NAME":null,"PHONE":[{"VALUE":null,"VALUE_TYPE":"WORK"}],"EMAIL":[{"VALUE":null,"VALUE_TYPE":"WORK"}],"COMMENTS":null,"TRACE":"{\u0022url\u0022:\u0022https:\/\/tingerplast.ru\/account\/auth\/\u0022,\u0022device\u0022:{\u0022isMobile\u0022:false},\u0022tags\u0022:{\u0022ts\u0022:1721390861,\u0022list\u0022:{},\u0022gclid\u0022:null},\u0022client\u0022:{\u0022yaId\u0022:\u002217213908614547571\u0022},\u0022pages\u0022:{\u0022list\u0022:[[\u0022https:\/\/tingerplast.ru\/account\/restore-password\/\u0022,1721390978,\u0022\u0412\u043e\u0441\u0441\u0442\u0430\u043d\u043e\u0432\u043b\u0435\u043d\u0438\u0435 \u043f\u0430\u0440\u043e\u043b\u044f\u0022],[\u0022https:\/\/tingerplast.ru\/account\/\u0022,1721394028,\u0022\u0410\u0432\u0442\u043e\u0440\u0438\u0437\u0430\u0446\u0438\u044f\u0022],[\u0022https:\/\/tingerplast.ru\/thanks\/\u0022,1721394054,\u0022\u0421\u043f\u0430\u0441\u0438\u0431\u043e \u0437\u0430 \u0437\u0430\u044f\u0432\u043a\u0443\u0022],[\u0022https:\/\/tingerplast.ru\/account\/auth\/\u0022,1721394118,\u0022\u0412\u0445\u043e\u0434 \u0432 \u0430\u043a\u043a\u0430\u0443\u043d\u0442 \u0434\u0438\u043b\u0435\u0440\u0430\u0022]]},\u0022gid\u0022:null,\u0022previous\u0022:{\u0022list\u0022:[]}}","UF_CRM_1517561552":"3345886"}}},"result":{"result":530914,"time":{"start":1721394133.4265029,"finish":1721394135.2460101,"duration":1.8195071220397949,"processing":1.7676210403442383,"date_start":"2024-07-19T16:02:13+03:00","date_finish":"2024-07-19T16:02:15+03:00","operating_reset_at":1721394733,"operating":6.8982617855072021}}}