{"url":"https:\/\/tinger.bitrix24.ru\/rest\/190\/dsdwvrccjexvxocc\/crm.contact.add.json","info":{"url":"https:\/\/tinger.bitrix24.ru\/rest\/190\/dsdwvrccjexvxocc\/crm.contact.add.json","content_type":"application\/json; charset=utf-8","http_code":200,"header_size":1103,"request_size":209,"filetime":-1,"ssl_verify_result":0,"redirect_count":0,"total_time":0.351802,"namelookup_time":0.000886,"connect_time":0.0096,"pretransfer_time":0.022433,"size_upload":183,"size_download":227,"speed_download":646,"speed_upload":521,"download_content_length":-1,"upload_content_length":183,"starttransfer_time":0.022439,"redirect_time":0,"redirect_url":"","primary_ip":"46.235.53.69","certinfo":[],"primary_port":443,"local_ip":"89.223.125.210","local_port":34580,"http_version":3,"protocol":2,"ssl_verifyresult":0,"scheme":"HTTPS","appconnect_time_us":22297,"connect_time_us":9600,"namelookup_time_us":886,"pretransfer_time_us":22433,"redirect_time_us":0,"starttransfer_time_us":22439,"total_time_us":351802},"params":{"method":"crm.contact.add","params":{"fields":{"UF_CRM_566E8F1A1E899":170,"PHONE":[{"VALUE":"","VALUE_TYPE":"WORK"}],"EMAIL":[{"VALUE":null,"VALUE_TYPE":"WORK"}],"NAME":""}}},"result":{"result":31838,"time":{"start":1648109995.754242,"finish":1648109996.023076,"duration":0.26883411407470703,"processing":0.23839879035949707,"date_start":"2022-03-24T11:19:55+03:00","date_finish":"2022-03-24T11:19:56+03:00"}}}