{"url":"https:\/\/tinger.bitrix24.ru\/rest\/190\/42tc2gxq8od2858i\/crm.lead.add.json","info":{"url":"https:\/\/tinger.bitrix24.ru\/rest\/190\/42tc2gxq8od2858i\/crm.lead.add.json","content_type":"application\/json; charset=utf-8","http_code":200,"header_size":1099,"request_size":206,"filetime":-1,"ssl_verify_result":0,"redirect_count":0,"total_time":3.351944,"namelookup_time":0.001593,"connect_time":0.0029060000000000002,"pretransfer_time":0.011389,"size_upload":433,"size_download":288,"speed_download":85,"speed_upload":129,"download_content_length":-1,"upload_content_length":433,"starttransfer_time":0.011391999999999999,"redirect_time":0,"redirect_url":"","primary_ip":"178.132.201.51","certinfo":[],"primary_port":443,"local_ip":"188.225.57.79","local_port":41850,"http_version":3,"protocol":2,"ssl_verifyresult":0,"scheme":"HTTPS","appconnect_time_us":11271,"connect_time_us":2906,"namelookup_time_us":1593,"pretransfer_time_us":11389,"redirect_time_us":0,"starttransfer_time_us":11392,"total_time_us":3351944},"params":{"method":"crm.lead.add","params":{"fields":{"SOURCE_ID":"WEB","ASSIGNED_BY_ID":58,"TITLE":"TINGER.RU | \u041a\u0443\u043f\u0438\u0442\u044c TINGER Track 2","TAG":"TINGER.RU","NAME":"\u041b\u0435\u0448\u0430","SECOND_NAME":"","LAST_NAME":"","UF_CRM_1517561552":"3312454","PHONE":[{"VALUE":"+7 (791) 208-30-49","VALUE_TYPE":"WORK"}],"UF_CRM_1449663065":64}}},"result":{"result":426016,"time":{"start":1676910483.7810559,"finish":1676910486.968092,"duration":3.1870360374450684,"processing":3.0902109146118164,"date_start":"2023-02-20T19:28:03+03:00","date_finish":"2023-02-20T19:28:06+03:00","operating_reset_at":1676911083,"operating":43.658137321472168}}}