{"url":"https:\/\/tinger.bitrix24.ru\/rest\/190\/42tc2gxq8od2858i\/crm.lead.add.json","info":{"url":"https:\/\/tinger.bitrix24.ru\/rest\/190\/42tc2gxq8od2858i\/crm.lead.add.json","content_type":"application\/json; charset=utf-8","http_code":200,"header_size":1029,"request_size":207,"filetime":-1,"ssl_verify_result":0,"redirect_count":0,"total_time":2.3356849999999998,"namelookup_time":0.002111,"connect_time":0.016833999999999998,"pretransfer_time":0.034874000000000002,"size_upload":3296,"size_download":289,"speed_download":123,"speed_upload":1411,"download_content_length":-1,"upload_content_length":3296,"starttransfer_time":0.034875999999999997,"redirect_time":0,"redirect_url":"","primary_ip":"178.132.201.52","certinfo":[],"primary_port":443,"local_ip":"188.225.57.79","local_port":54556,"http_version":3,"protocol":2,"ssl_verifyresult":0,"scheme":"HTTPS","appconnect_time_us":34737,"connect_time_us":16834,"namelookup_time_us":2111,"pretransfer_time_us":34874,"redirect_time_us":0,"starttransfer_time_us":34876,"total_time_us":2335685},"params":{"method":"crm.lead.add","params":{"fields":{"NAME":"\u0442\u0430\u0442\u044c\u044f\u043d\u0430","PHONE":[{"VALUE":"+7 (905) 996-68-70","VALUE_TYPE":"WORK"}],"EMAIL":[{"VALUE":null,"VALUE_TYPE":"WORK"}],"COMMENTS":null,"TRACE":"{\u0022url\u0022:\u0022https:\/\/tingard.ru\/?utm_source=yandex_kirill\u0026utm_medium=cpc\u0026utm_campaign=pogreba_rozn_umnaya_copy_11_04\u0026utm_content=13300555425\u0026utm_term=---autotargeting\u0026roistat=direct14_context_13300555425_---autotargeting\u0026roistat_referrer=app.minigames.mail.ru\u0026roistat_pos=none_0\u0026yclid=2320545937802395647\u0022,\u0022device\u0022:{\u0022isMobile\u0022:false},\u0022tags\u0022:{\u0022ts\u0022:1703509364,\u0022list\u0022:{\u0022utm_source\u0022:\u0022yandex_kirill\u0022,\u0022utm_medium\u0022:\u0022cpc\u0022,\u0022utm_campaign\u0022:\u0022pogreba_rozn_umnaya_copy_11_04\u0022,\u0022utm_content\u0022:\u002213300555425\u0022,\u0022utm_term\u0022:\u0022---autotargeting\u0022},\u0022gclid\u0022:null},\u0022client\u0022:{\u0022yaId\u0022:\u00221703177599593455698\u0022},\u0022pages\u0022:{\u0022list\u0022:[[\u0022https:\/\/tingard.ru\/?utm_source=yandex_kirill\u0026utm_medium=cpc\u0026utm_campaign=pogreba_rozn_umnaya_copy_11_04\u0026utm_content=13300555425\u0026utm_term=---autotargeting\u0026roistat=direct14_context_13300555425_---autotargeting\u0026roistat_referrer=app.minigames.mail.ru\u0026roistat_pos=none_0\u0026yclid=2320545937802395647\u0022,1703509365,\u0022TINGARD \u2014 \u0431\u0435\u0441\u0448\u043e\u0432\u043d\u044b\u0439 \u043f\u043b\u0430\u0441\u0442\u0438\u043a\u043e\u0432\u044b\u0439 \u043f\u043e\u0433\u0440\u0435\u0431 \u2116\u0022]]},\u0022gid\u0022:\u0022w7t3156e7uswvcoce0n8sj37rui7z643\u0022,\u0022previous\u0022:{\u0022list\u0022:[{\u0022url\u0022:\u0022https:\/\/tingard.ru\/?utm_source=yandex_kirill\u0026utm_medium=cpc\u0026utm_campaign=pogreba_rozn_umnaya_copy_11_04\u0026utm_content=13300555425\u0026utm_term=---autotargeting\u0026roistat=direct14_context_13300555425_---autotargeting\u0026roistat_referrer=app.minigames.mail.ru\u0026roistat_pos=none_0\u0026yclid=2320545937802395647\u0022,\u0022device\u0022:{\u0022isMobile\u0022:false},\u0022tags\u0022:{\u0022ts\u0022:1703412039,\u0022list\u0022:{\u0022utm_source\u0022:\u0022yandex_kirill\u0022,\u0022utm_medium\u0022:\u0022cpc\u0022,\u0022utm_campaign\u0022:\u0022pogreba_rozn_umnaya_copy_11_04\u0022,\u0022utm_content\u0022:\u002213300555425\u0022,\u0022utm_term\u0022:\u0022---autotargeting\u0022},\u0022gclid\u0022:null},\u0022client\u0022:{\u0022yaId\u0022:\u00221703177599593455698\u0022},\u0022pages\u0022:{\u0022list\u0022:[[\u0022https:\/\/tingard.ru\/?utm_source=yandex_kirill\u0026utm_medium=cpc\u0026utm_campaign=pogreba_rozn_umnaya_copy_11_04\u0026utm_content=13300555425\u0026utm_term=---autotargeting\u0026roistat=direct14_context_13300555425_---autotargeting\u0026roistat_referrer=app.minigames.mail.ru\u0026roistat_pos=none_0\u0026yclid=12038420394969661439\u0022,1703412039,\u0022TINGARD \u2014 \u0431\u0435\u0441\u0448\u043e\u0432\u043d\u044b\u0439 \u043f\u043b\u0430\u0441\u0442\u0438\u043a\u043e\u0432\u044b\u0439 \u043f\u043e\u0433\u0440\u0435\u0431 \u2116\u0022]]},\u0022gid\u0022:\u0022w7t3156e7uswvcoce0n8sj37rui7z643\u0022}]}}","TITLE":"\u0417\u0430\u043a\u0430\u0437\u0430\u0442\u044c \u043f\u043e\u0433\u0440\u0435\u0431","UF_CRM_1449663065":68,"ASSIGNED_BY_ID":58,"SOURCE_ID":9}}},"result":{"result":489384,"time":{"start":1703510590.2178781,"finish":1703510592.4095111,"duration":2.1916329860687256,"processing":2.1543540954589844,"date_start":"2023-12-25T16:23:10+03:00","date_finish":"2023-12-25T16:23:12+03:00","operating_reset_at":1703511190,"operating":2.1543190479278564}}}