{"url":"https:\/\/tinger.bitrix24.ru\/rest\/190\/42tc2gxq8od2858i\/crm.contact.add.json","info":{"url":"https:\/\/tinger.bitrix24.ru\/rest\/190\/42tc2gxq8od2858i\/crm.contact.add.json","content_type":"application\/json; charset=utf-8","http_code":200,"header_size":1030,"request_size":209,"filetime":-1,"ssl_verify_result":0,"redirect_count":0,"total_time":0.30917699999999998,"namelookup_time":0.001358,"connect_time":0.01026,"pretransfer_time":0.028877,"size_upload":358,"size_download":289,"speed_download":935,"speed_upload":1158,"download_content_length":-1,"upload_content_length":358,"starttransfer_time":0.028879999999999999,"redirect_time":0,"redirect_url":"","primary_ip":"89.208.228.119","certinfo":[],"primary_port":443,"local_ip":"188.225.57.79","local_port":46484,"http_version":3,"protocol":2,"ssl_verifyresult":0,"scheme":"HTTPS","appconnect_time_us":28798,"connect_time_us":10260,"namelookup_time_us":1358,"pretransfer_time_us":28877,"redirect_time_us":0,"starttransfer_time_us":28880,"total_time_us":309177},"params":{"method":"crm.contact.add","params":{"fields":{"UF_CRM_566E8F1A1E899":170,"ASSIGNED_BY_ID":50856,"PHONE":[{"VALUE":"+7 (993) 191-62-39","VALUE_TYPE":"WORK"}],"EMAIL":[{"VALUE":"romka.yudin217@gmail.com","VALUE_TYPE":"WORK"}],"NAME":"\u0420\u043e\u043c\u0430\u043d \u042e\u0434\u0438\u043d"}}},"result":{"result":65928,"time":{"start":1701252417.103591,"finish":1701252417.330277,"duration":0.22668600082397461,"processing":0.17414402961730957,"date_start":"2023-11-29T13:06:57+03:00","date_finish":"2023-11-29T13:06:57+03:00","operating_reset_at":1701253017,"operating":0.17412590980529785}}}