{"url":"https:\/\/tinger.bitrix24.ru\/rest\/190\/42tc2gxq8od2858i\/crm.lead.add.json","info":{"url":"https:\/\/tinger.bitrix24.ru\/rest\/190\/42tc2gxq8od2858i\/crm.lead.add.json","content_type":"application\/json; charset=utf-8","http_code":200,"header_size":923,"request_size":207,"filetime":-1,"ssl_verify_result":0,"redirect_count":0,"total_time":1.4397390000000001,"namelookup_time":0.015483,"connect_time":0.025659999999999999,"pretransfer_time":0.071375999999999995,"size_upload":1741,"size_download":262,"speed_download":182,"speed_upload":1209,"download_content_length":-1,"upload_content_length":1741,"starttransfer_time":0.071379999999999999,"redirect_time":0,"redirect_url":"","primary_ip":"89.208.228.119","certinfo":[],"primary_port":443,"local_ip":"188.225.57.79","local_port":33942,"http_version":3,"protocol":2,"ssl_verifyresult":0,"scheme":"HTTPS","appconnect_time_us":71235,"connect_time_us":25660,"namelookup_time_us":15483,"pretransfer_time_us":71376,"redirect_time_us":0,"starttransfer_time_us":71380,"total_time_us":1439739},"params":{"method":"crm.lead.add","params":{"fields":{"UF_CRM_1449663065":"68","SOURCE_ID":"CONFERENCE","ASSIGNED_BY_ID":58,"TITLE":"\u0417\u0430\u043a\u0430\u0437 \u0441 \u0441\u0430\u0439\u0442\u0430 (\u0438\u0437 \u043a\u043e\u0440\u0437\u0438\u043d\u044b)","NAME":"\u0415\u043b\u0435\u043d\u0430","PHONE":[{"VALUE":"+7 (932) 055-22-22","VALUE_TYPE":"WORK"}],"EMAIL":[{"VALUE":null,"VALUE_TYPE":"WORK"}],"COMMENTS":"\u003Cb\u003E\u0421\u043e\u0441\u0442\u0430\u0432 \u0437\u0430\u043a\u0430\u0437\u0430:\u003C\/b\u003E \u003Cbr\u003E\u041b\u0438\u0441\u0442 \u041f\u041d\u0414 3000x1500x8 \u043c\u043c, \u0447\u0451\u0440\u043d\u044b\u0439 (6 \u0448\u0442.), \u043d\u0430 \u0441\u0443\u043c\u043c\u0443 47\u0026nbsp;748 \u0440\u0443\u0431.\u003Cbr\u003E\u041e\u0431\u0449\u0430\u044f \u0441\u0443\u043c\u043c\u0430 \u0437\u0430\u043a\u0430\u0437\u0430: \u003Cb\u003E47\u0026nbsp;748 \u0440\u0443\u0431.\u003C\/b\u003E","TRACE":"{\u0022url\u0022:\u0022https:\/\/tingerplast.ru\/cart\/\u0022,\u0022device\u0022:{\u0022isMobile\u0022:true},\u0022tags\u0022:{\u0022ts\u0022:1765523832,\u0022list\u0022:{},\u0022gclid\u0022:null},\u0022client\u0022:{\u0022yaId\u0022:\u00221765684137713713679\u0022},\u0022pages\u0022:{\u0022list\u0022:[[\u0022https:\/\/tingerplast.ru\/listovoy-plastik-pnd\/list-pnd-3000x1500x8-mm-chyernyy\/?ysclid=mix3htb580946101435\u0022,1765684135,\u0022\u041b\u0438\u0441\u0442 \u041f\u041d\u0414 3000x1500x8 \u043c\u043c, \u0447\u0451\u0440\u043d\u044b\u0439\u0022],[\u0022https:\/\/tingerplast.ru\/cart\/\u0022,1765684439,\u0022\u041a\u043e\u0440\u0437\u0438\u043d\u0430\u0022]]},\u0022gid\u0022:null,\u0022previous\u0022:{\u0022list\u0022:[]}}","UF_CRM_1517561552":"3835343"}}},"result":{"result":635524,"time":{"start":1765684450,"finish":1765684452.0027981,"duration":2.0027980804443359,"processing":2,"date_start":"2025-12-14T06:54:10+03:00","date_finish":"2025-12-14T06:54:12+03:00","operating_reset_at":1765685050,"operating":1.2854628562927246}}}