{"url":"https:\/\/tinger.bitrix24.ru\/rest\/190\/42tc2gxq8od2858i\/crm.lead.add.json","info":{"url":"https:\/\/tinger.bitrix24.ru\/rest\/190\/42tc2gxq8od2858i\/crm.lead.add.json","content_type":"application\/json; charset=utf-8","http_code":200,"header_size":1097,"request_size":206,"filetime":-1,"ssl_verify_result":0,"redirect_count":0,"total_time":1.864065,"namelookup_time":0.013543,"connect_time":0.015046,"pretransfer_time":0.020642,"size_upload":787,"size_download":256,"speed_download":137,"speed_upload":422,"download_content_length":-1,"upload_content_length":787,"starttransfer_time":0.020648,"redirect_time":0,"redirect_url":"","primary_ip":"178.132.201.52","certinfo":[],"primary_port":443,"local_ip":"89.223.125.210","local_port":24130,"http_version":3,"protocol":2,"ssl_verifyresult":0,"scheme":"HTTPS","appconnect_time_us":20491,"connect_time_us":15046,"namelookup_time_us":13543,"pretransfer_time_us":20642,"redirect_time_us":0,"starttransfer_time_us":20648,"total_time_us":1864065},"params":{"method":"crm.lead.add","params":{"fields":{"SOURCE_ID":"WEB","ASSIGNED_BY_ID":58,"TITLE":"TINGER.RU | \u0417\u0430\u044f\u0432\u043a\u0430 \u043d\u0430 \u0422\u041e","TAG":"TINGER.RU","NAME":"zxczxc","EMAIL":[{"VALUE":"dfgdf@sddfsdf.com","VALUE_TYPE":"WORK"}],"COMMENTS":"\u003Cb\u003E\u0412\u0435\u0437\u0434\u0435\u0445\u043e\u0434: \u003C\/b\u003E\u0412\u044b\u0431\u0435\u0440\u0438\u0442\u0435 \u043c\u043e\u0434\u0435\u043b\u044c \u0432\u0435\u0437\u0434\u0435\u0445\u043e\u0434\u0430*\u003Cbr\u003E\u003Cb\u003E\u041f\u0440\u043e\u0431\u0435\u0433: \u003C\/b\u003E35454ew\u003Cbr\u003E\u003Cb\u003E\u041f\u043e\u0436\u0435\u043b\u0430\u043d\u0438\u044f \u043a\u043b\u0438\u0435\u043d\u0442\u0430: \u003C\/b\u003Esdfgdgf dsfgsdfgds","UF_CRM_1449663065":"4788"}}},"result":{"result":374366,"time":{"start":1652866156.085979,"finish":1652866157.855667,"duration":1.7696881294250488,"processing":1.7047622203826904,"date_start":"2022-05-18T12:29:16+03:00","date_finish":"2022-05-18T12:29:17+03:00","operating":5.987331867218018}}}