{"url":"https:\/\/tinger.bitrix24.ru\/rest\/190\/42tc2gxq8od2858i\/crm.lead.add.json","info":{"url":"https:\/\/tinger.bitrix24.ru\/rest\/190\/42tc2gxq8od2858i\/crm.lead.add.json","content_type":"application\/json; charset=utf-8","http_code":200,"header_size":1034,"request_size":207,"filetime":-1,"ssl_verify_result":0,"redirect_count":0,"total_time":3.6821220000000001,"namelookup_time":0.001652,"connect_time":0.027,"pretransfer_time":0.066350999999999993,"size_upload":1651,"size_download":287,"speed_download":77,"speed_upload":448,"download_content_length":-1,"upload_content_length":1651,"starttransfer_time":0.066352999999999995,"redirect_time":0,"redirect_url":"","primary_ip":"46.235.53.69","certinfo":[],"primary_port":443,"local_ip":"188.225.57.79","local_port":41284,"http_version":3,"protocol":2,"ssl_verifyresult":0,"scheme":"HTTPS","appconnect_time_us":66238,"connect_time_us":27000,"namelookup_time_us":1652,"pretransfer_time_us":66351,"redirect_time_us":0,"starttransfer_time_us":66353,"total_time_us":3682122},"params":{"method":"crm.lead.add","params":{"fields":{"UF_CRM_1449663065":"16452","SOURCE_ID":98,"ASSIGNED_BY_ID":58,"TITLE":"\u0417\u0430\u043a\u0430\u0437\u0430\u0442\u044c \u0451\u043c\u043a\u043e\u0441\u0442\u044c","NAME":"\u0418\u0432\u0430\u043d","PHONE":[{"VALUE":"+7 (951) 811-02-62","VALUE_TYPE":"WORK"}],"EMAIL":[{"VALUE":null,"VALUE_TYPE":"WORK"}],"COMMENTS":"","TRACE":"{\u0022url\u0022:\u0022https:\/\/pt.tingerplast.ru\/?utm_source=yandex\u0026utm_medium=cpc\u0026utm_campaign=emkosti_mk_rf\u0026utm_content=14436425780\u0026utm_term=---autotargeting\u0026yclid=4242645089028202415\u0022,\u0022ref\u0022:\u0022https:\/\/yandex.ru\/games\/app\/210231\u0022,\u0022device\u0022:{\u0022isMobile\u0022:false},\u0022tags\u0022:{\u0022ts\u0022:1690357218,\u0022list\u0022:{\u0022utm_source\u0022:\u0022yandex\u0022,\u0022utm_medium\u0022:\u0022cpc\u0022,\u0022utm_campaign\u0022:\u0022emkosti_mk_rf\u0022,\u0022utm_content\u0022:\u002214436425780\u0022,\u0022utm_term\u0022:\u0022---autotargeting\u0022},\u0022gclid\u0022:null},\u0022client\u0022:{\u0022yaId\u0022:\u00221690357218564145270\u0022},\u0022pages\u0022:{\u0022list\u0022:[[\u0022https:\/\/pt.tingerplast.ru\/?utm_source=yandex\u0026utm_medium=cpc\u0026utm_campaign=emkosti_mk_rf\u0026utm_content=14436425780\u0026utm_term=---autotargeting\u0026yclid=4242645089028202415\u0022,1690357218,\u0022\u041f\u043b\u0430\u0441\u0442\u0438\u043a\u043e\u0432\u044b\u0435 \u0451\u043c\u043a\u043e\u0441\u0442\u0438 \u0431\u043e\u043b\u044c\u0448\u043e\u0433\u043e \u043e\u0431\u044a\u0451\u043c\u0430 \u043e\u0442 \u043f\u0022]]},\u0022gid\u0022:null,\u0022previous\u0022:{\u0022list\u0022:[]}}"}}},"result":{"result":459016,"time":{"start":1690357223.1614671,"finish":1690357226.644398,"duration":3.4829308986663818,"processing":3.4410748481750488,"date_start":"2023-07-26T10:40:23+03:00","date_finish":"2023-07-26T10:40:26+03:00","operating_reset_at":1690357823,"operating":6.738889217376709}}}