{"url":"https:\/\/tinger.bitrix24.ru\/rest\/190\/42tc2gxq8od2858i\/crm.lead.add.json","info":{"url":"https:\/\/tinger.bitrix24.ru\/rest\/190\/42tc2gxq8od2858i\/crm.lead.add.json","content_type":"application\/json; charset=utf-8","http_code":200,"header_size":925,"request_size":206,"filetime":-1,"ssl_verify_result":0,"redirect_count":0,"total_time":1.7177070000000001,"namelookup_time":0.013998,"connect_time":0.023257,"pretransfer_time":0.045629999999999997,"size_upload":469,"size_download":263,"speed_download":153,"speed_upload":273,"download_content_length":-1,"upload_content_length":469,"starttransfer_time":0.045635000000000002,"redirect_time":0,"redirect_url":"","primary_ip":"46.235.53.58","certinfo":[],"primary_port":443,"local_ip":"188.225.57.79","local_port":44924,"http_version":3,"protocol":2,"ssl_verifyresult":0,"scheme":"HTTPS","appconnect_time_us":45316,"connect_time_us":23257,"namelookup_time_us":13998,"pretransfer_time_us":45630,"redirect_time_us":0,"starttransfer_time_us":45635,"total_time_us":1717707},"params":{"method":"crm.lead.add","params":{"fields":{"NAME":"\u0418\u0432\u0430\u043d ","EMAIL":[{"VALUE":"ip.tupikin@mail.ru","VALUE_TYPE":"WORK"}],"TRACE":null,"UF_CRM_1736853511":null,"UF_CRM_1736853555":null,"UF_CRM_1736853537":null,"UF_CRM_1517561552":"nocookie","COMMENTS":"89883311188","TITLE":"\u0421\u0432\u044f\u0437\u0430\u0442\u044c\u0441\u044f \u0441 \u043f\u0440\u043e\u0438\u0437\u0432\u043e\u0434\u0438\u0442\u0435\u043b\u0435\u043c","UF_CRM_1449663065":68,"ASSIGNED_BY_ID":58,"SOURCE_ID":9}}},"result":{"result":634680,"time":{"start":1765030682,"finish":1765030684.0842271,"duration":2.0842270851135254,"processing":2,"date_start":"2025-12-06T17:18:02+03:00","date_finish":"2025-12-06T17:18:04+03:00","operating_reset_at":1765031282,"operating":1.5810179710388184}}}