{"url":"https:\/\/tinger.bitrix24.ru\/rest\/190\/42tc2gxq8od2858i\/crm.contact.add.json","info":{"url":"https:\/\/tinger.bitrix24.ru\/rest\/190\/42tc2gxq8od2858i\/crm.contact.add.json","content_type":"application\/json; charset=utf-8","http_code":200,"header_size":1128,"request_size":209,"filetime":-1,"ssl_verify_result":0,"redirect_count":0,"total_time":1.4748779999999999,"namelookup_time":0.001243,"connect_time":0.0027920000000000002,"pretransfer_time":0.010357,"size_upload":270,"size_download":286,"speed_download":194,"speed_upload":183,"download_content_length":-1,"upload_content_length":270,"starttransfer_time":0.010359,"redirect_time":0,"redirect_url":"","primary_ip":"178.132.201.52","certinfo":[],"primary_port":443,"local_ip":"188.225.57.79","local_port":45402,"http_version":3,"protocol":2,"ssl_verifyresult":0,"scheme":"HTTPS","appconnect_time_us":10290,"connect_time_us":2792,"namelookup_time_us":1243,"pretransfer_time_us":10357,"redirect_time_us":0,"starttransfer_time_us":10359,"total_time_us":1474878},"params":{"method":"crm.contact.add","params":{"fields":{"UF_CRM_566E8F1A1E899":170,"PHONE":[{"VALUE":"+7 (998) 888-85-55","VALUE_TYPE":"WORK"}],"EMAIL":[{"VALUE":"test@trttttwwq.com","VALUE_TYPE":"WORK"}],"NAME":"zxczxc"}}},"result":{"result":63102,"time":{"start":1688537653.1645601,"finish":1688537654.5796361,"duration":1.4150760173797607,"processing":1.321727991104126,"date_start":"2023-07-05T09:14:13+03:00","date_finish":"2023-07-05T09:14:14+03:00","operating_reset_at":1688538253,"operating":1.321688175201416}}}